{
  "id": "measure_nox_changed",
  "title": {
    "en": "The NOx value has changed",
    "nl": "De NOx-waarde is veranderd",
    "da": "NOx-værdien er ændret",
    "de": "Der NOx-Wert hat sich geändert",
    "es": "El valor de NOx ha cambiado",
    "fr": "La valeur du NOx a changé",
    "it": "Il valore di NOx è cambiato",
    "no": "NOx-verdien har endret seg",
    "sv": "NOx-värdet har ändrats",
    "pl": "Wartość NOx się zmieniła",
    "ru": "Значение NOx изменилось",
    "ko": "NOx 값이 변경되었습니다"
  },
  "titleFormatted": {
    "en": "The NOx value has changed",
    "nl": "De NOx-waarde is veranderd",
    "da": "NOx-værdien er ændret",
    "de": "Der NOx-Wert hat sich geändert",
    "es": "El valor de NOx ha cambiado",
    "fr": "La valeur du NOx a changé",
    "it": "Il valore di NOx è cambiato",
    "no": "NOx-verdien har endret seg",
    "sv": "NOx-värdet har ändrats",
    "pl": "Wartość NOx się zmieniła",
    "ru": "Значение NOx изменилось",
    "ko": "NOx 값이 변경되었습니다"
  },
  "args": [
    {
      "type": "device",
      "name": "device",
      "filter": "driver_id=indoor|outdoor"
    }
  ],
  "tokens": [
    {
      "name": "measure_nox",
      "title": {
        "en": "NOx",
        "nl": "NOx",
        "da": "NOx",
        "de": "NOx",
        "es": "NOx",
        "fr": "NOx",
        "it": "NOx",
        "no": "NOx",
        "sv": "NOx",
        "pl": "NOx",
        "ru": "NOx",
        "ko": "NOx"
      },
      "type": "number",
      "example": 2
    }
  ]
}